gpaa_scraper/__init__.py
gpaa_scraper/browser.py
gpaa_scraper/container.py
gpaa_scraper/exception.py
gpaa_scraper/helper.py
gpaa_scraper/parsing.py
gpaa_scraper/utils.py
Google_Paa_Scraper-0.0.11.dist-info/LICENSE
Google_Paa_Scraper-0.0.11.dist-info/METADATA
Google_Paa_Scraper-0.0.11.dist-info/WHEEL
Google_Paa_Scraper-0.0.11.dist-info/top_level.txt
Google_Paa_Scraper-0.0.11.dist-info/RECORD
