Metadata-Version: 2.1
Name: Google-Paa-Scraper
Version: 0.0.11
Summary: Get data from googles people also ask section.
Home-page: https://github.com/huzai786/Google-Paa-Scraper
Author: Muhammad Huzaifa
Author-email: muhammadhuzaifagamer123@gmail.com
License: MIT
Keywords: google-paa,People-Also-Ask,Google-PAA
Classifier: Programming Language :: Python :: 3.7
Classifier: Programming Language :: Python :: 3.8
Classifier: Programming Language :: Python :: 3.9
Classifier: Programming Language :: Python :: 3.10
Classifier: Operating System :: OS Independent
Classifier: License :: OSI Approved :: MIT License
Classifier: Intended Audience :: Developers
License-File: LICENSE
Requires-Dist: webdriver-manager
Requires-Dist: beautifulsoup4
Requires-Dist: selenium
Requires-Dist: lxml
